django_microservice_common/__init__.py
django_microservice_common/api/__init__.py
django_microservice_common/api/api_view.py
django_microservice_common/api/class_responses/__init__.py
django_microservice_common/api/class_responses/error_response.py
django_microservice_common/api/data_responses/__init__.py
django_microservice_common/api/data_responses/data_response.py
django_microservice_common/api/exception_handlers.py
django_microservice_common/api/pagination.py
django_microservice_common/api/serializers/__init__.py
django_microservice_common/api/serializers/common_serializer.py
django_microservice_common/api/serializers/custom_fields/__init__.py
django_microservice_common/api/serializers/custom_fields/fields.py
django_microservice_common/api/utils.py
django_microservice_common/apps.py
django_microservice_common/authorization/__init__.py
django_microservice_common/authorization/enums.py
django_microservice_common/authorization/exceptions.py
django_microservice_common/authorization/grants.py
django_microservice_common/authorization/grants_func.py
django_microservice_common/authorization/mapper.py
django_microservice_common/authorization/roles.py
django_microservice_common/authorization/validators.py
django_microservice_common/dependency_manager/__init__.py
django_microservice_common/dependency_manager/container.py
django_microservice_common/dependency_manager/registry.py
django_microservice_common/exceptions/__init__.py
django_microservice_common/exceptions/exceptions.py
django_microservice_common/models/__init__.py
django_microservice_common/models/base_model.py
django_microservice_common/services/__init__.py
django_microservice_common/services/services.py
django_microservice_common/types/__init__.py
django_microservice_common/types/types.py
django_microservice_common/utils/__init__.py
django_microservice_common/utils/django/__init__.py
django_microservice_common/utils/django/utils.py
django_microservice_common/utils/drf/__init__.py
django_microservice_common-0.2.1.dist-info/METADATA
django_microservice_common-0.2.1.dist-info/WHEEL
django_microservice_common-0.2.1.dist-info/RECORD
